CmakeCookbookZhongwenban/README.md
CmakeCookbookZhongwenban/__init__.py
CmakeCookbookZhongwenban/__main__.py
CmakeCookbookZhongwenban/file.epub
CmakeCookbookZhongwenban/index.html
CmakeCookbookZhongwenban/css/__init__.py
CmakeCookbookZhongwenban/css/annotations.css
CmakeCookbookZhongwenban/css/main.css
CmakeCookbookZhongwenban/css/normalize.css
CmakeCookbookZhongwenban/css/popup.css
CmakeCookbookZhongwenban/font/__init__.py
CmakeCookbookZhongwenban/font/fontello.eot
CmakeCookbookZhongwenban/font/fontello.svg
CmakeCookbookZhongwenban/font/fontello.ttf
CmakeCookbookZhongwenban/font/fontello.woff
CmakeCookbookZhongwenban/img/__init__.py
CmakeCookbookZhongwenban/img/annotator-glyph-sprite.png
CmakeCookbookZhongwenban/img/annotator-icon-sprite.png
CmakeCookbookZhongwenban/img/apple-touch-icon.png
CmakeCookbookZhongwenban/img/cancelfullscreen.png
CmakeCookbookZhongwenban/img/close.png
CmakeCookbookZhongwenban/img/fullscreen.png
CmakeCookbookZhongwenban/img/loader.gif
CmakeCookbookZhongwenban/img/menu-icon.png
CmakeCookbookZhongwenban/img/save.png
CmakeCookbookZhongwenban/img/saved.png
CmakeCookbookZhongwenban/img/settings-s.png
CmakeCookbookZhongwenban/img/settings.png
CmakeCookbookZhongwenban/img/star.png
CmakeCookbookZhongwenban/js/__init__.py
CmakeCookbookZhongwenban/js/epub.js
CmakeCookbookZhongwenban/js/epub.min.js
CmakeCookbookZhongwenban/js/epub.min.map
CmakeCookbookZhongwenban/js/hooks.min.js
CmakeCookbookZhongwenban/js/hooks.min.map
CmakeCookbookZhongwenban/js/reader.js
CmakeCookbookZhongwenban/js/reader.js.map
CmakeCookbookZhongwenban/js/reader.min.js
CmakeCookbookZhongwenban/js/reader.min.map
CmakeCookbookZhongwenban/js/hooks/__init__.py
CmakeCookbookZhongwenban/js/hooks/extensions/__init__.py
CmakeCookbookZhongwenban/js/hooks/extensions/highlight.js
CmakeCookbookZhongwenban/js/libs/__init__.py
CmakeCookbookZhongwenban/js/libs/jquery.min.js
CmakeCookbookZhongwenban/js/libs/localforage.min.js
CmakeCookbookZhongwenban/js/libs/screenfull.js
cmake_cookbook_zhongwenban-2024.3.5.0.dist-info/METADATA
cmake_cookbook_zhongwenban-2024.3.5.0.dist-info/WHEEL
cmake_cookbook_zhongwenban-2024.3.5.0.dist-info/entry_points.txt
cmake_cookbook_zhongwenban-2024.3.5.0.dist-info/top_level.txt
cmake_cookbook_zhongwenban-2024.3.5.0.dist-info/RECORD
